kplot/__init__.py
kplot/dark.py
kplot/kg.py
kplot-0.0.18.dist-info/LICENSE
kplot-0.0.18.dist-info/METADATA
kplot-0.0.18.dist-info/WHEEL
kplot-0.0.18.dist-info/top_level.txt
kplot-0.0.18.dist-info/RECORD
